[
    {
        "type": "ScreenAndWidget",
        "_type": "ScreenAndWidget",
        "id": "RedLoginScreen",
        "name": "RedLoginScreen",
        "category": "Screens",
        "subcategory": "AAA",
        "screens": {
          "RedLoginScreen": {
            "x":0,
            "y":0,
            "h": "$100%",
            "w": "$100%",
            "name": "RedLoginScreen",
            "type": "Screen",
            "style": {
              "background": {
                "colors": [
                  {
                    "c": "#f24e4e",
                    "p": 0.8
                  },
                  {
                    "c": "#e70606",
                    "p": 97.9
                  }
                ],
                "gradient": true,
                "direction": 90,
                "gradientHeight": 300,
                "gradientWidth": 30,
                "selectedHandle": 0
              }
            },
            "has": {
              "image": true
            },
            "props": {
              "start": true
            },
            "children": [
              "RedLoginScreen0",
              "RedLoginScreen1",
              "RedLoginScreen2"
            ],
            "id": "RedLoginScreen",
            "_type": "Screen",
            "category": "WireFrame",
            "subcategory": "XXX"
          }
        },
        "widgets": {
          "RedLoginScreen0": {
            "type": "Button",
            "name": "Box",
            "x": 377,
            "y": 143,
            "w": 526,
            "h": 435,
            "props": {
              "label": ""
            },
            "has": {
              "backgroundColor": true,
              "border": true,
              "label": true,
              "padding": true,
              "onclick": true
            },
            "actions": {},
            "style": {
              "fontSize": 14,
              "fontFamily": "Helvetica Neue,Helvetica,Arial,sans-serif",
              "textAlign": "left",
              "letterSpacing": 0,
              "lineHeight": 1.4,
              "color": "#ffffff",
              "borderTopRightRadius": 5,
              "borderTopLeftRadius": 5,
              "borderBottomRightRadius": 5,
              "borderBottomLeftRadius": 5,
              "borderTopWidth": 0,
              "borderBottomWidth": 0,
              "borderRightWidth": 0,
              "borderLeftWidth": 0,
              "borderTopColor": "#333333",
              "borderBottomColor": "#333333",
              "borderRightColor": "#333333",
              "borderLeftColor": "#333333",
              "background": "#ffffff",
              "paddingTop": 0,
              "paddingBottom": 0,
              "paddingLeft": 0,
              "paddingRight": 0,
              "textShadow": null,
              "boxShadow": {
                "v": 0,
                "h": 0,
                "b": 17,
                "s": 11,
                "c": "rgba(0, 0, 0, 0.25)"
              }
            },
            "id": "RedLoginScreen0",
            "_type": "Widget",
            "z": null,
            "template": null
          },
          "RedLoginScreen1": {
            "id": "RedLoginScreen1",
            "type": "Icon",
            "name": "Icon",
            "x": 408,
            "y": 198,
            "w": 40,
            "h": 40,
            "props": {},
            "has": {
              "onclick": true,
              "data": true
            },
            "actions": {},
            "style": {
              "borderTopRightRadius": 0,
              "borderTopLeftRadius": 0,
              "borderBottomRightRadius": 0,
              "borderBottomLeftRadius": 0,
              "borderTopWidth": 0,
              "borderBottomWidth": 0,
              "borderRightWidth": 0,
              "borderLeftWidth": 0,
              "borderTopColor": "#333333",
              "borderBottomColor": "#333333",
              "borderRightColor": "#333333",
              "borderLeftColor": "#333333",
              "color": "#333333",
              "icon": "mdi mdi-fleur-de-lis"
            },
            "_type": "Widget",
            "z": null,
            "template": null
          },
          "RedLoginScreen2": {
            "id": "RedLoginScreen2",
            "type": "Icon",
            "name": "Icon 1",
            "x": 418,
            "y": 280,
            "w": 40,
            "h": 40,
            "props": {},
            "has": {
              "onclick": true,
              "data": true
            },
            "actions": {},
            "style": {
              "borderTopRightRadius": 0,
              "borderTopLeftRadius": 0,
              "borderBottomRightRadius": 0,
              "borderBottomLeftRadius": 0,
              "borderTopWidth": 0,
              "borderBottomWidth": 0,
              "borderRightWidth": 0,
              "borderLeftWidth": 0,
              "borderTopColor": "#333333",
              "borderBottomColor": "#333333",
              "borderRightColor": "#333333",
              "borderLeftColor": "#333333",
              "color": "#333333",
              "icon": "mdi mdi-ninja"
            },
            "_type": "Widget",
            "z": null,
            "template": null
          }
        },
        "lines": {},
        "groups": {}
      }
]