[
    {
        "id": "CardUser",
        "type": "Group",
        "_type": "Group",
        "name": "Card User",
        "category": "Composite",
        "subcategory": "F",
        "children": [
          {
            "type": "Button",
            "name": "Background",
            "x": 0,
            "y": 0,
            "w": 320,
            "h": 260,
            "props": {
              "label": "",
              "paddingSnap": true
            },
            "has": {
              "backgroundColor": true,
              "border": true,
              "label": true,
              "padding": true,
              "onclick": true
            },
            "actions": {},
            "style": {
              "fontSize": 14,
              "fontFamily": "Helvetica Neue,Helvetica,Arial,sans-serif",
              "textAlign": "left",
              "letterSpacing": 0,
              "lineHeight": 1.4,
              "color": "#ffffff",
              "borderTopRightRadius": 8,
              "borderTopLeftRadius": 8,
              "borderBottomRightRadius": 8,
              "borderBottomLeftRadius": 8,
              "borderTopWidth": 1,
              "borderBottomWidth": 1,
              "borderRightWidth": 1,
              "borderLeftWidth": 1,
              "borderTopColor": "#dedede",
              "borderBottomColor": "#dedede",
              "borderRightColor": "#dedede",
              "borderLeftColor": "#dedede",
              "background": "#ffffff",
              "paddingTop": 16,
              "paddingBottom": 16,
              "paddingLeft": 16,
              "paddingRight": 16,
              "textShadow": null,
              "boxShadow": null,
              "borderTopStyle": "solid",
              "borderBottomStyle": "solid",
              "borderRightStyle": "solid",
              "borderLeftStyle": "solid"
            },
            "id": "CardUser0",
            "_type": "Widget",
            "z": null,
            "template": null
          },
          {
            "type": "Label",
            "name": "Label 1",
            "x": 16,
            "y": 128,
            "w": 286,
            "h": 32,
            "props": {
              "label": "Name Lastname",
              "resize": {
                "right": true,
                "up": true,
                "left": true,
                "down": false,
                "fixedHorizontal": false,
                "fixedVertical": true
              }
            },
            "has": {
              "label": true,
              "padding": true,
              "advancedText": true
            },
            "style": {
              "fontSize": 20,
              "fontFamily": "Helvetica Neue,Helvetica,Arial,sans-serif",
              "textAlign": "center",
              "letterSpacing": 0,
              "lineHeight": 1,
              "color": "#000000",
              "textShadow": null,
              "fontWeight": "bold"
            },
            "id": "CardUser1",
            "_type": "Widget",
            "z": null,
            "template": null
          },
          {
            "type": "Label",
            "name": "Label 1",
            "x": 16,
            "y": 160,
            "w": 286,
            "h": 24,
            "props": {
              "label": "name@company.com",
              "resize": {
                "right": true,
                "up": true,
                "left": true,
                "down": false,
                "fixedHorizontal": false,
                "fixedVertical": true
              }
            },
            "has": {
              "label": true,
              "padding": true,
              "advancedText": true
            },
            "style": {
              "fontSize": 14,
              "fontFamily": "Helvetica Neue,Helvetica,Arial,sans-serif",
              "textAlign": "center",
              "letterSpacing": 0,
              "lineHeight": 1,
              "color": "#a4a4a4",
              "textShadow": null,
              "fontWeight": ""
            },
            "id": "CardUser2",
            "_type": "Widget",
            "z": null,
            "template": null
          },
          {
            "type": "Image",
            "name": "Image",
            "x": 112,
            "y": 16,
            "w": 96,
            "h": 96,
            "props": {
              "resize": {
                "right": true,
                "up": true,
                "left": true,
                "down": true,
                "fixedHorizontal": false,
                "fixedVertical": false
              }
            },
            "has": {
              "onclick": true,
              "backgroundImage": true,
              "borderRadius": true,
              "border": true,
              "iconPlaceholder": true
            },
            "actions": {},
            "style": {
              "backgroundImage": null,
              "borderTopWidth": 0,
              "borderBottomWidth": 0,
              "borderRightWidth": 0,
              "borderLeftWidth": 0,
              "borderTopRightRadius": 96,
              "borderTopLeftRadius": 96,
              "borderBottomRightRadius": 96,
              "borderBottomLeftRadius": 96,
              "borderTopColor": "#000000",
              "borderBottomColor": "#000000",
              "borderRightColor": "#000000",
              "borderLeftColor": "#000000",
              "borderTopStyle": "solid",
              "borderBottomStyle": "solid",
              "borderRightStyle": "solid",
              "borderLeftStyle": "solid"
            },
            "id": "Card_Right3",
            "_type": "Widget",
            "z": null,
            "template": null
          },
          {
            "type": "Button",
            "name": "Button",
            "x": 95,
            "y": 209,
            "w": 32,
            "h": 32,
            "props": {
              "label": "",
              "paddingSnap": true,
              "resize": {
                "right": false,
                "up": false,
                "left": false,
                "down": true,
                "fixedHorizontal": true,
                "fixedVertical": true
              }
            },
            "has": {
              "backgroundColor": true,
              "border": true,
              "label": true,
              "padding": true,
              "onclick": true
            },
            "actions": {},
            "style": {
              "fontSize": 14,
              "fontFamily": "Helvetica Neue,Helvetica,Arial,sans-serif",
              "textAlign": "left",
              "letterSpacing": 0,
              "lineHeight": 1.4,
              "color": "#ffffff",
              "borderTopRightRadius": 128,
              "borderTopLeftRadius": 128,
              "borderBottomRightRadius": 128,
              "borderBottomLeftRadius": 128,
              "borderTopWidth": 0,
              "borderBottomWidth": 0,
              "borderRightWidth": 0,
              "borderLeftWidth": 0,
              "borderTopColor": "#000000",
              "borderBottomColor": "#000000",
              "borderRightColor": "#000000",
              "borderLeftColor": "#000000",
              "background": "#dedede",
              "paddingTop": 0,
              "paddingBottom": 0,
              "paddingLeft": 0,
              "paddingRight": 0,
              "textShadow": null,
              "borderTopStyle": "solid",
              "borderBottomStyle": "solid",
              "borderRightStyle": "solid",
              "borderLeftStyle": "solid"
            },
            "id": "CardUser4",
            "_type": "Widget",
            "z": null,
            "template": null
          },
          {
            "id": "CardUser5",
            "type": "Icon",
            "name": "Email",
            "x": 103,
            "y": 217,
            "w": 16,
            "h": 16,
            "props": {
              "resize": {
                "right": false,
                "up": true,
                "left": true,
                "down": false,
                "fixedHorizontal": true,
                "fixedVertical": true
              }
            },
            "has": {
              "onclick": true,
              "data": true
            },
            "actions": {},
            "style": {
              "borderTopRightRadius": 0,
              "borderTopLeftRadius": 0,
              "borderBottomRightRadius": 0,
              "borderBottomLeftRadius": 0,
              "borderTopWidth": 0,
              "borderBottomWidth": 0,
              "borderRightWidth": 0,
              "borderLeftWidth": 0,
              "borderTopColor": "#333333",
              "borderBottomColor": "#333333",
              "borderRightColor": "#333333",
              "borderLeftColor": "#333333",
              "color": "#333333",
              "icon": "mdi mdi-email-outline"
            },
            "_type": "Widget",
            "z": null,
            "template": null
          },
          {
            "type": "Button",
            "name": "PhoneBackground",
            "x": 143,
            "y": 209,
            "w": 32,
            "h": 32,
            "props": {
              "label": "",
              "paddingSnap": true,
              "resize": {
                "right": false,
                "up": false,
                "left": false,
                "down": true,
                "fixedHorizontal": true,
                "fixedVertical": true
              }
            },
            "has": {
              "backgroundColor": true,
              "border": true,
              "label": true,
              "padding": true,
              "onclick": true
            },
            "actions": {},
            "style": {
              "fontSize": 14,
              "fontFamily": "Helvetica Neue,Helvetica,Arial,sans-serif",
              "textAlign": "left",
              "letterSpacing": 0,
              "lineHeight": 1.4,
              "color": "#ffffff",
              "borderTopRightRadius": 128,
              "borderTopLeftRadius": 128,
              "borderBottomRightRadius": 128,
              "borderBottomLeftRadius": 128,
              "borderTopWidth": 0,
              "borderBottomWidth": 0,
              "borderRightWidth": 0,
              "borderLeftWidth": 0,
              "borderTopColor": "#000000",
              "borderBottomColor": "#000000",
              "borderRightColor": "#000000",
              "borderLeftColor": "#000000",
              "background": "#dedede",
              "paddingTop": 0,
              "paddingBottom": 0,
              "paddingLeft": 0,
              "paddingRight": 0,
              "textShadow": null,
              "borderTopStyle": "solid",
              "borderBottomStyle": "solid",
              "borderRightStyle": "solid",
              "borderLeftStyle": "solid"
            },
            "id": "CardUser6",
            "_type": "Widget",
            "z": null,
            "template": null
          },
          {
            "id": "CardUser7",
            "type": "Icon",
            "name": "Phone",
            "x": 151,
            "y": 217,
            "w": 16,
            "h": 16,
            "props": {
              "resize": {
                "right": false,
                "up": true,
                "left": true,
                "down": false,
                "fixedHorizontal": true,
                "fixedVertical": true
              }
            },
            "has": {
              "onclick": true,
              "data": true
            },
            "actions": {},
            "style": {
              "borderTopRightRadius": 0,
              "borderTopLeftRadius": 0,
              "borderBottomRightRadius": 0,
              "borderBottomLeftRadius": 0,
              "borderTopWidth": 0,
              "borderBottomWidth": 0,
              "borderRightWidth": 0,
              "borderLeftWidth": 0,
              "borderTopColor": "#333333",
              "borderBottomColor": "#333333",
              "borderRightColor": "#333333",
              "borderLeftColor": "#333333",
              "color": "#333333",
              "icon": "mdi mdi-phone-hangup-outline"
            },
            "_type": "Widget",
            "z": null,
            "template": null
          },
          {
            "type": "Button",
            "name": "ChatBackground",
            "x": 191,
            "y": 209,
            "w": 32,
            "h": 32,
            "props": {
              "label": "",
              "paddingSnap": true,
              "resize": {
                "right": false,
                "up": false,
                "left": false,
                "down": true,
                "fixedHorizontal": true,
                "fixedVertical": true
              }
            },
            "has": {
              "backgroundColor": true,
              "border": true,
              "label": true,
              "padding": true,
              "onclick": true
            },
            "actions": {},
            "style": {
              "fontSize": 14,
              "fontFamily": "Helvetica Neue,Helvetica,Arial,sans-serif",
              "textAlign": "left",
              "letterSpacing": 0,
              "lineHeight": 1.4,
              "color": "#ffffff",
              "borderTopRightRadius": 128,
              "borderTopLeftRadius": 128,
              "borderBottomRightRadius": 128,
              "borderBottomLeftRadius": 128,
              "borderTopWidth": 0,
              "borderBottomWidth": 0,
              "borderRightWidth": 0,
              "borderLeftWidth": 0,
              "borderTopColor": "#000000",
              "borderBottomColor": "#000000",
              "borderRightColor": "#000000",
              "borderLeftColor": "#000000",
              "background": "#dedede",
              "paddingTop": 0,
              "paddingBottom": 0,
              "paddingLeft": 0,
              "paddingRight": 0,
              "textShadow": null,
              "borderTopStyle": "solid",
              "borderBottomStyle": "solid",
              "borderRightStyle": "solid",
              "borderLeftStyle": "solid"
            },
            "id": "CardUser8",
            "_type": "Widget",
            "z": null,
            "template": null
          },
          {
            "id": "CardUser9",
            "type": "Icon",
            "name": "Chat",
            "x": 199,
            "y": 217,
            "w": 16,
            "h": 16,
            "props": {
              "resize": {
                "right": false,
                "up": true,
                "left": true,
                "down": false,
                "fixedHorizontal": true,
                "fixedVertical": true
              }
            },
            "has": {
              "onclick": true,
              "data": true
            },
            "actions": {},
            "style": {
              "borderTopRightRadius": 0,
              "borderTopLeftRadius": 0,
              "borderBottomRightRadius": 0,
              "borderBottomLeftRadius": 0,
              "borderTopWidth": 0,
              "borderBottomWidth": 0,
              "borderRightWidth": 0,
              "borderLeftWidth": 0,
              "borderTopColor": "#333333",
              "borderBottomColor": "#333333",
              "borderRightColor": "#333333",
              "borderLeftColor": "#333333",
              "color": "#333333",
              "icon": "mdi mdi-chat-outline"
            },
            "_type": "Widget",
            "z": null,
            "template": null
          }
        ]
      }
]